ssh_known_hosts_edit/__init__.py
ssh_known_hosts_edit/ssh_known_hosts_edit.py
ssh_known_hosts_edit-0.2.0.dist-info/METADATA
ssh_known_hosts_edit-0.2.0.dist-info/WHEEL
ssh_known_hosts_edit-0.2.0.dist-info/licenses/LICENSE
ssh_known_hosts_edit-0.2.0.dist-info/RECORD
