Metadata-Version: 2.3
Name: ssh-known-hosts-edit
Version: 0.2.0
Summary: OpenSSH known_hosts file edit tool
Author-email: Wim Van de Meersche <wim.vandemeersche@ugent.be>
License-File: LICENSE
Classifier: Development Status :: 4 - Beta
Classifier: Intended Audience :: Developers
Classifier: License :: OSI Approved :: MIT License
Classifier: Programming Language :: Python :: 3
Classifier: Programming Language :: Python :: 3.7
Classifier: Programming Language :: Python :: 3.8
Classifier: Programming Language :: Python :: 3.9
Classifier: Topic :: Internet
Classifier: Topic :: Security
Classifier: Topic :: Software Development :: Libraries
Requires-Python: >=3.7
Provides-Extra: test
Requires-Dist: pytest<8,>=7.4.3; extra == 'test'
